make_responsive_images/__init__.py
make_responsive_images/__main__.py
make_responsive_images/main.py
make_responsive_images/utils.py
make_responsive_images-0.1.17.dist-info/AUTHORS.md
make_responsive_images-0.1.17.dist-info/LICENSE
make_responsive_images-0.1.17.dist-info/METADATA
make_responsive_images-0.1.17.dist-info/WHEEL
make_responsive_images-0.1.17.dist-info/entry_points.txt
make_responsive_images-0.1.17.dist-info/RECORD
