Metadata-Version: 2.1
Name: make-responsive-images
Version: 0.1.17
Summary: Generate responsive images for your website, so you can use srcset in your <img> tags and serve an optimal image to each device that views your site.
Home-page: https://mccarthysean.dev/make-responsive-images
License: MIT
Keywords: responsive,images,generator
Author: Sean McCarthy
Author-email: sean.mccarthy@hotmail.com
Requires-Python: >=3.8,<4.0
Classifier: License :: OSI Approved :: MIT License
Classifier: Programming Language :: Python :: 3
Classifier: Programming Language :: Python :: 3.8
Classifier: Programming Language :: Python :: 3.9
Classifier: Programming Language :: Python :: 3.10
Classifier: Programming Language :: Python :: 3.11
Classifier: Programming Language :: Python :: 3.12
Requires-Dist: Pillow (>=10.4.0,<11.0.0)
Requires-Dist: colorama (>=0.4.6,<0.5.0)
Requires-Dist: shellingham (>=1.5.4,<2.0.0)
Requires-Dist: typer (>=0.12.5,<0.13.0)
Project-URL: Documentation, https://mccarthysean.dev/make-responsive-images
Project-URL: Repository, https://github.com/mccarthysean/make-responsive-images
Project-URL: Sean's Blog, https://mccarthysean.dev
Project-URL: Sean's Company, https://myijack.com
